README.md
funcoperators.py
setup.py
funcoperators.egg-info/PKG-INFO
funcoperators.egg-info/SOURCES.txt
funcoperators.egg-info/dependency_links.txt
funcoperators.egg-info/top_level.txt