Metadata-Version: 2.1
Name: funcoperators
Version: 0.8.6
Summary: Allow natural function notations like (1,2) /dot/ (3,4) for dot((1,2), (3,4)) or 1 /frac/ 3 for Fraction(1,3), pipes and other useful operators to functions.
Home-page: https://github.com/robertvandeneynde/python
Author: Robert Vanden Eynde
Author-email: robertvandeneynde@hotmail.com
License: UNKNOWN
Platform: UNKNOWN
